peppercornenumerator/__init__.py
peppercornenumerator/condense.py
peppercornenumerator/enumerator.py
peppercornenumerator/input.py
peppercornenumerator/objects.py
peppercornenumerator/output.py
peppercornenumerator/peppercorn.py
peppercornenumerator/pilsimulator.py
peppercornenumerator/ratemodel.py
peppercornenumerator/reactions.py
peppercornenumerator/utils.py
peppercornenumerator-1.1.1.dist-info/entry_points.txt
peppercornenumerator-1.1.1.dist-info/LICENSE
peppercornenumerator-1.1.1.dist-info/WHEEL
peppercornenumerator-1.1.1.dist-info/METADATA
peppercornenumerator-1.1.1.dist-info/RECORD
