Metadata-Version: 2.1
Name: peppercornenumerator
Version: 1.1.1
Summary: Domain-level nucleic acid reaction enumerator
Author: Casey Grun, Karthik Sarma, Brian Wolfe, Seung Woo Shin
Author-email: Stefan Badelt <bad-ants-fleet@posteo.eu>, Erik Winfree <winfree@caltech.edu>
Maintainer-email: Stefan Badelt <bad-ants-fleet@posteo.eu>
Requires-Python: >=3.8
Classifier: Intended Audience :: Science/Research
Classifier: Programming Language :: Python :: 3.8
Classifier: Programming Language :: Python :: 3.9
Classifier: Programming Language :: Python :: 3.10
Classifier: Programming Language :: Python :: 3.11
Classifier: License :: OSI Approved :: MIT License
Classifier: Development Status :: 5 - Production/Stable
Requires-Dist: numpy
Requires-Dist: pandas
Requires-Dist: natsort
Requires-Dist: dsdobjects>=0.8
Requires-Dist: pytest ; extra == "dev"
Requires-Dist: pytest-cov ; extra == "dev"
Requires-Dist: codecov ; extra == "dev"
Project-URL: Home, http://www.github.com/DNA-and-Natural-Algorithms-Group/peppercorn
Provides-Extra: dev
